README.md
exodusutils/__init__.py
exodusutils/app_utils.py
exodusutils/configuration/__init__.py
exodusutils/configuration/configs/configs.py
exodusutils/configuration/configs/grpc.py
exodusutils/configuration/configs/minio.py
exodusutils/configuration/configs/mongodb.py
exodusutils/configuration/configs/utils.py
exodusutils/configuration/mongo_instance.py
exodusutils/constants.py
exodusutils/enums.py
exodusutils/exceptions/__init__.py
exodusutils/exceptions/exceptions.py
exodusutils/feature_engineering/__init__.py
exodusutils/feature_engineering/label_encoding.py
exodusutils/feature_engineering/one_hot_encoding.py
exodusutils/feature_engineering/time_component_encoding.py
exodusutils/frame_manipulation.py
exodusutils/frames.py
exodusutils/infra/__init__.py
exodusutils/infra/grpc_client.py
exodusutils/infra/prefect.py
exodusutils/internal/__init__.py
exodusutils/internal/process_unit.py
exodusutils/migration/__init__.py
exodusutils/migration/base_migration.py
exodusutils/migration/migration.py
exodusutils/model_store.py
exodusutils/predict/__init__.py
exodusutils/preprocessing/__init__.py
exodusutils/preprocessing/column_cardinality_limiter.py
exodusutils/preprocessing/constant_columns_remover.py
exodusutils/preprocessing/imputation.py
exodusutils/schemas/__init__.py
exodusutils/schemas/auc_metric.py
exodusutils/schemas/input_file.py
exodusutils/schemas/model.py
exodusutils/schemas/requests.py
exodusutils/schemas/responses.py
exodusutils/schemas/scores.py
exodusutils/schemas/simple_iid_request.py
exodusutils/schemas/timegroup.py
exodusutils/schemas/uri.py
exodusutils-0.3.53.dist-info/LICENSE
exodusutils-0.3.53.dist-info/METADATA
exodusutils-0.3.53.dist-info/WHEEL
exodusutils-0.3.53.dist-info/RECORD
