Metadata-Version: 2.1
Name: exodusutils
Version: 0.3.53
Summary: Utility functions and helper classes for Exodus project
License: Apache-2.0
Author: Tsung-Ju Lii
Author-email: andylii@mobagel.com
Requires-Python: >=3.8.0,<4.0.0
Classifier: Development Status :: 1 - Planning
Classifier: Intended Audience :: Developers
Classifier: Intended Audience :: Information Technology
Classifier: License :: OSI Approved :: Apache Software License
Classifier: Operating System :: OS Independent
Classifier: Programming Language :: Python :: 3
Classifier: Programming Language :: Python :: 3.8
Classifier: Programming Language :: Python :: 3.9
Classifier: Programming Language :: Python :: 3.10
Classifier: Programming Language :: Python :: 3.11
Classifier: Programming Language :: Python :: 3.8
Classifier: Programming Language :: Python :: Implementation :: PyPy
Classifier: Topic :: Internet
Classifier: Topic :: Internet :: WWW/HTTP
Classifier: Topic :: Software Development :: Libraries
Classifier: Topic :: Software Development :: Libraries :: Application Frameworks
Classifier: Topic :: Software Development :: Libraries :: Python Modules
Requires-Dist: colorama (>=0.4.4,<0.5.0)
Requires-Dist: minio (>=7.1.11,<8.0.0)
Requires-Dist: numpy (>=1.19.4)
Requires-Dist: pandas (>=1.0.5)
Requires-Dist: pydantic (>=1.9.0,<2.0.0)
Requires-Dist: pymongo[encryption] (>=4.0.1,<5.0.0)
Requires-Dist: python-levenshtein (>=0.21.0,<0.22.0)
Requires-Dist: requests (>=2.28.1,<3.0.0)
Requires-Dist: scikit-learn (>=0.23.1)
